Register_file_32x32/rtl/top.v
module register_file (
	input wire clk,
	input wire rst_n,
	input wire ce,
	input wire rd_en1,
	input wire rd_en2,
	input wire [4:0] rd_addr1,
	input wire [4:0] rd_addr2,
	input wire wr_en,
	input wire [4:0] wr_addr,
	input wire [31:0] wr_data,
	output reg [31:0] rd_data1,
	output reg [31:0] rd_data2
);

// Mang thanh ghi: 32 thanh ghi, moi thanh ghi rong 32 bit
reg [31:0] reg_file[31:0];
integer i;

// Cong doc co dieu kien (kich hoat boi chip enable va read enable)
always @(posedge clk or negedge rst_n) begin
	if(!rst_n) begin
		rd_data1 <= 32'h00000000;
		rd_data2 <= 32'h00000000;
	end else begin
		rd_data1 <= (ce && rd_en1) ? reg_file[rd_addr1] : 32'h00000000;
		rd_data2 <= (ce && rd_en2) ? reg_file[rd_addr2] : 32'h00000000;
	end
end

always @(posedge clk or negedge rst_n) begin
	if(!rst_n) begin
		for (i = 0; i < 32; i = i + 1) begin
			reg_file[i] <= 32'h00000000;
		end
	end else begin
		reg_file[wr_addr] <= (ce && wr_en) ? wr_data : reg_file[wr_addr];
	end
end

endmodule

Register_file_32x32/tb/test_bench.v
`timescale 1ns/1ps
module test_bench;
	reg clk;
    	reg rst_n;
	reg ce;
	reg rd_en1;
	reg rd_en2;
	reg [4:0] rd_addr1;
	reg [4:0] rd_addr2;
	reg wr_en;
	reg [4:0] wr_addr;
	reg [31:0] wr_data;
	wire [31:0] rd_data1;
	wire [31:0] rd_data2;
	
	register_file dut(.*);	

	parameter CLK_PERIOD = 5;
	integer i;
	integer rad_data;
	
	task write_data;
		input [4:0] exp_wr_addr;
		input [31:0] exp_wr_data;
		begin
			wr_en = 1;
			wr_addr = exp_wr_addr;
			wr_data = exp_wr_data;
			@(posedge clk);
			wr_en = 0;
		end
	endtask

	task read_data;
		input exp_rd_en1;
		input exp_rd_en2;
		input [4:0] exp_rd_addr1;
		input [4:0] exp_rd_addr2;
		begin
			rd_en1 = exp_rd_en1;
			rd_en2 = exp_rd_en2;
			rd_addr1 = exp_rd_addr1;
			rd_addr2 = exp_rd_addr2;
			@(posedge clk);
		end
	endtask

	task verify;
		input [31:0] exp_rd_data1;
		input [31:0] exp_rd_data2;
		begin
			$display("At time: %t, ce = 1'b%b, rd_en1 = 1'b%b, rd_en2 = 1'b%b, rd_addr1 = 5'b%b, rd_addr2 = 5'b%b, wr_en = 1'b%b, wr_data = 32'h%h",$time, ce, rd_en1, rd_en2, rd_addr1, rd_addr2, wr_en, wr_addr, wr_data);
			if (rd_data1 == exp_rd_data1 && rd_data2 == exp_rd_data2) begin
				$display("--------------------------------------------------------------------------------------------------------------------------------");
				$display("PASSED: Expected data1: 32'h%h, Got data1: 32'h%h, Expected_data2: 32'h%h, Got data2:32'h%h", exp_rd_data1, rd_data1, exp_rd_data2, rd_data2);
				$display("--------------------------------------------------------------------------------------------------------------------------------");
			end else begin
				$display("--------------------------------------------------------------------------------------------------------------------------------");
				$display("FAILED: Expected data1: 32'h%h, Got data1: 32'h%h, Expected_data2: 32'h%h, Got data2:32'h%h", exp_rd_data1, rd_data1, exp_rd_data2, rd_data2);
				$display("--------------------------------------------------------------------------------------------------------------------------------");
			end
		end
	endtask

	initial begin
		clk = 0;
		forever #CLK_PERIOD clk = ~clk;
	end

	initial begin
		$dumpfile("test_bench.vcd");
		$dumpvars(0, test_bench);

		$display("--------------------------------------------------------------------------------------------------------------------------------------------------");
		$display("-------------------------------------------------TESTBENCH FOR REGISTER FILE 32X32----------------------------------------------------------------");
		$display("--------------------------------------------------------------------------------------------------------------------------------------------------");
		
		rst_n = 0;
		@(posedge clk);
		verify(32'h00000000, 32'h00000000);
		
		rst_n = 1;
		ce = 0;
		@(posedge clk);
		write_data(5'b00000, 32'hffffffff);
		read_data(1,1,5'b00000, 5'b00001);
		verify(32'h00000000, 32'h00000000);
		
		ce = 1;
		@(posedge clk);
		write_data(5'b00000, 32'hffffffff);
		read_data(1,0,5'b00000, 5'b00001);
		verify(32'hffffffff, 32'h00000000);

		for (i = 0; i < 32; i = i + 1) begin
			rad_data = $urandom % (1 << 31);
			write_data(i, rad_data);
			read_data(1,0,i, 5'b00000);
			verify(rad_data, 32'h00000000);
		end
		for (i = 0; i < 32; i = i + 1) begin
			rad_data = $urandom % (1 << 31);
			write_data(i, rad_data);
			read_data(0,1,5'b00000,i);
			verify(32'h00000000,rad_data);
		end
		#100;
		$finish;
	end
endmodule

Register_file_32x32/sim/test_bench.vcd
$date
	Sat Jan 25 17:18:19 2025
$end
$version
	Icarus Verilog
$end
$timescale
	1ps
$end
$scope module test_bench $end
$var wire 32 ! rd_data2 [31:0] $end
$var wire 32 " rd_data1 [31:0] $end
$var parameter 32 # CLK_PERIOD $end
$var reg 1 $ ce $end
$var reg 1 % clk $end
$var reg 5 & rd_addr1 [4:0] $end
$var reg 5 ' rd_addr2 [4:0] $end
$var reg 1 ( rd_en1 $end
$var reg 1 ) rd_en2 $end
$var reg 1 * rst_n $end
$var reg 5 + wr_addr [4:0] $end
$var reg 32 , wr_data [31:0] $end
$var reg 1 - wr_en $end
$var integer 32 . i [31:0] $end
$var integer 32 / rad_data [31:0] $end
$scope module dut $end
$var wire 1 $ ce $end
$var wire 1 % clk $end
$var wire 5 0 rd_addr1 [4:0] $end
$var wire 5 1 rd_addr2 [4:0] $end
$var wire 1 ( rd_en1 $end
$var wire 1 ) rd_en2 $end
$var wire 1 * rst_n $end
$var wire 5 2 wr_addr [4:0] $end
$var wire 32 3 wr_data [31:0] $end
$var wire 1 - wr_en $end
$var reg 32 4 rd_data1 [31:0] $end
$var reg 32 5 rd_data2 [31:0] $end
$var integer 32 6 i [31:0] $end
$upscope $end
$scope task read_data $end
$var reg 5 7 exp_rd_addr1 [4:0] $end
$var reg 5 8 exp_rd_addr2 [4:0] $end
$var reg 1 9 exp_rd_en1 $end
$var reg 1 : exp_rd_en2 $end
$upscope $end
$scope task verify $end
$var reg 32 ; exp_rd_data1 [31:0] $end
$var reg 32 < exp_rd_data2 [31:0] $end
$upscope $end
$scope task write_data $end
$var reg 5 = exp_wr_addr [4:0] $end
$var reg 32 > exp_wr_data [31:0] $end
$upscope $end
$upscope $end
$enddefinitions $end
$comment Show the parameter values. $end
$dumpall
b101 #
$end
#0
$dumpvars
bx >
bx =
bx <
bx ;
x:
x9
bx 8
bx 7
b100000 6
b0 5
b0 4
bx 3
bx 2
bx 1
bx 0
bx /
bx .
x-
bx ,
bx +
0*
x)
x(
bx '
bx &
0%
x$
b0 "
b0 !
$end
#5000
0$
1*
b0 <
b0 ;
1%
#10000
0%
#15000
b11111111111111111111111111111111 ,
b11111111111111111111111111111111 3
b0 +
b0 2
1-
b11111111111111111111111111111111 >
b0 =
1%
#20000
0%
#25000
b1 '
b1 1
b0 &
b0 0
1)
1(
b1 8
b0 7
1:
19
0-
1%
#30000
0%
#35000
1$
1%
#40000
0%
#45000
1-
1%
#50000
0%
#55000
b11111111111111111111111111111111 "
b11111111111111111111111111111111 4
0)
0:
0-
1%
#60000
0%
#65000
b10010000101010011010100100100 ,
b10010000101010011010100100100 3
1-
b10010000101010011010100100100 >
b10010000101010011010100100100 /
b0 .
b11111111111111111111111111111111 ;
1%
#70000
0%
#75000
b10010000101010011010100100100 "
b10010000101010011010100100100 4
b0 '
b0 1
b0 8
0-
1%
#80000
0%
#85000
b1000000100010010101111010000001 ,
b1000000100010010101111010000001 3
b1 +
b1 2
1-
b1000000100010010101111010000001 >
b1 =
b1000000100010010101111010000001 /
b1 .
b10010000101010011010100100100 ;
1%
#90000
0%
#95000
b1000000100010010101111010000001 "
b1000000100010010101111010000001 4
b1 &
b1 0
b1 7
0-
1%
#100000
0%
#105000
b100100001001101011000001001 ,
b100100001001101011000001001 3
b10 +
b10 2
1-
b100100001001101011000001001 >
b10 =
b100100001001101011000001001 /
b10 .
b1000000100010010101111010000001 ;
1%
#110000
0%
#115000
b100100001001101011000001001 "
b100100001001101011000001001 4
b10 &
b10 0
b10 7
0-
1%
#120000
0%
#125000
b110001111100000101011001100011 ,
b110001111100000101011001100011 3
b11 +
b11 2
1-
b110001111100000101011001100011 >
b11 =
b110001111100000101011001100011 /
b11 .
b100100001001101011000001001 ;
1%
#130000
0%
#135000
b110001111100000101011001100011 "
b110001111100000101011001100011 4
b11 &
b11 0
b11 7
0-
1%
#140000
0%
#145000
b110101110010111101100001101 ,
b110101110010111101100001101 3
b100 +
b100 2
1-
b110101110010111101100001101 >
b100 =
b110101110010111101100001101 /
b100 .
b110001111100000101011001100011 ;
1%
#150000
0%
#155000
b110101110010111101100001101 "
b110101110010111101100001101 4
b100 &
b100 0
b100 7
0-
1%
#160000
0%
#165000
b1000110110111111001100110001101 ,
b1000110110111111001100110001101 3
b101 +
b101 2
1-
b1000110110111111001100110001101 >
b101 =
b1000110110111111001100110001101 /
b101 .
b110101110010111101100001101 ;
1%
#170000
0%
#175000
b1000110110111111001100110001101 "
b1000110110111111001100110001101 4
b101 &
b101 0
b101 7
0-
1%
#180000
0%
#185000
b110010110000101000010001100101 ,
b110010110000101000010001100101 3
b110 +
b110 2
1-
b110010110000101000010001100101 >
b110 =
b110010110000101000010001100101 /
b110 .
b1000110110111111001100110001101 ;
1%
#190000
0%
#195000
b110010110000101000010001100101 "
b110010110000101000010001100101 4
b110 &
b110 0
b110 7
0-
1%
#200000
0%
#205000
b1001001101110101001000010010 ,
b1001001101110101001000010010 3
b111 +
b111 2
1-
b1001001101110101001000010010 >
b111 =
b1001001101110101001000010010 /
b111 .
b110010110000101000010001100101 ;
1%
#210000
0%
#215000
b1001001101110101001000010010 "
b1001001101110101001000010010 4
b111 &
b111 0
b111 7
0-
1%
#220000
0%
#225000
b111100111110001100000001 ,
b111100111110001100000001 3
b1000 +
b1000 2
1-
b111100111110001100000001 >
b1000 =
b111100111110001100000001 /
b1000 .
b1001001101110101001000010010 ;
1%
#230000
0%
#235000
b111100111110001100000001 "
b111100111110001100000001 4
b1000 &
b1000 0
b1000 7
0-
1%
#240000
0%
#245000
b110110101111100110100001101 ,
b110110101111100110100001101 3
b1001 +
b1001 2
1-
b110110101111100110100001101 >
b1001 =
b110110101111100110100001101 /
b1001 .
b111100111110001100000001 ;
1%
#250000
0%
#255000
b110110101111100110100001101 "
b110110101111100110100001101 4
b1001 &
b1001 0
b1001 7
0-
1%
#260000
0%
#265000
b111011001000111111000101110110 ,
b111011001000111111000101110110 3
b1010 +
b1010 2
1-
b111011001000111111000101110110 >
b1010 =
b111011001000111111000101110110 /
b1010 .
b110110101111100110100001101 ;
1%
#270000
0%
#275000
b111011001000111111000101110110 "
b111011001000111111000101110110 4
b1010 &
b1010 0
b1010 7
0-
1%
#280000
0%
#285000
b11110100011011100110100111101 ,
b11110100011011100110100111101 3
b1011 +
b1011 2
1-
b11110100011011100110100111101 >
b1011 =
b11110100011011100110100111101 /
b1011 .
b111011001000111111000101110110 ;
1%
#290000
0%
#295000
b11110100011011100110100111101 "
b11110100011011100110100111101 4
b1011 &
b1011 0
b1011 7
0-
1%
#300000
0%
#305000
b1110110110101000101011111101101 ,
b1110110110101000101011111101101 3
b1100 +
b1100 2
1-
b1110110110101000101011111101101 >
b1100 =
b1110110110101000101011111101101 /
b1100 .
b11110100011011100110100111101 ;
1%
#310000
0%
#315000
b1110110110101000101011111101101 "
b1110110110101000101011111101101 4
b1100 &
b1100 0
b1100 7
0-
1%
#320000
0%
#325000
b1000110001011011111011110001100 ,
b1000110001011011111011110001100 3
b1101 +
b1101 2
1-
b1000110001011011111011110001100 >
b1101 =
b1000110001011011111011110001100 /
b1101 .
b1110110110101000101011111101101 ;
1%
#330000
0%
#335000
b1000110001011011111011110001100 "
b1000110001011011111011110001100 4
b1101 &
b1101 0
b1101 7
0-
1%
#340000
0%
#345000
b1111100111111011110100111111001 ,
b1111100111111011110100111111001 3
b1110 +
b1110 2
1-
b1111100111111011110100111111001 >
b1110 =
b1111100111111011110100111111001 /
b1110 .
b1000110001011011111011110001100 ;
1%
#350000
0%
#355000
b1111100111111011110100111111001 "
b1111100111111011110100111111001 4
b1110 &
b1110 0
b1110 7
0-
1%
#360000
0%
#365000
b1100011001101110010010011000110 ,
b1100011001101110010010011000110 3
b1111 +
b1111 2
1-
b1100011001101110010010011000110 >
b1111 =
b1100011001101110010010011000110 /
b1111 .
b1111100111111011110100111111001 ;
1%
#370000
0%
#375000
b1100011001101110010010011000110 "
b1100011001101110010010011000110 4
b1111 &
b1111 0
b1111 7
0-
1%
#380000
0%
#385000
b1100010111101111000010011000101 ,
b1100010111101111000010011000101 3
b10000 +
b10000 2
1-
b1100010111101111000010011000101 >
b10000 =
b1100010111101111000010011000101 /
b10000 .
b1100011001101110010010011000110 ;
1%
#390000
0%
#395000
b1100010111101111000010011000101 "
b1100010111101111000010011000101 4
b10000 &
b10000 0
b10000 7
0-
1%
#400000
0%
#405000
b1010101000100111101001010101010 ,
b1010101000100111101001010101010 3
b10001 +
b10001 2
1-
b1010101000100111101001010101010 >
b10001 =
b1010101000100111101001010101010 /
b10001 .
b1100010111101111000010011000101 ;
1%
#410000
0%
#415000
b1010101000100111101001010101010 "
b1010101000100111101001010101010 4
b10001 &
b10001 0
b10001 7
0-
1%
#420000
0%
#425000
b1110010101011111111011111100101 ,
b1110010101011111111011111100101 3
b10010 +
b10010 2
1-
b1110010101011111111011111100101 >
b10010 =
b1110010101011111111011111100101 /
b10010 .
b1010101000100111101001010101010 ;
1%
#430000
0%
#435000
b1110010101011111111011111100101 "
b1110010101011111111011111100101 4
b10010 &
b10010 0
b10010 7
0-
1%
#440000
0%
#445000
b111011110100100111001001110111 ,
b111011110100100111001001110111 3
b10011 +
b10011 2
1-
b111011110100100111001001110111 >
b10011 =
b111011110100100111001001110111 /
b10011 .
b1110010101011111111011111100101 ;
1%
#450000
0%
#455000
b111011110100100111001001110111 "
b111011110100100111001001110111 4
b10011 &
b10011 0
b10011 7
0-
1%
#460000
0%
#465000
b1001001100101101011000010010 ,
b1001001100101101011000010010 3
b10100 +
b10100 2
1-
b1001001100101101011000010010 >
b10100 =
b1001001100101101011000010010 /
b10100 .
b111011110100100111001001110111 ;
1%
#470000
0%
#475000
b1001001100101101011000010010 "
b1001001100101101011000010010 4
b10100 &
b10100 0
b10100 7
0-
1%
#480000
0%
#485000
b1000111111011001101101110001111 ,
b1000111111011001101101110001111 3
b10101 +
b10101 2
1-
b1000111111011001101101110001111 >
b10101 =
b1000111111011001101101110001111 /
b10101 .
b1001001100101101011000010010 ;
1%
#490000
0%
#495000
b1000111111011001101101110001111 "
b1000111111011001101101110001111 4
b10101 &
b10101 0
b10101 7
0-
1%
#500000
0%
#505000
b1111001001100000110100111110010 ,
b1111001001100000110100111110010 3
b10110 +
b10110 2
1-
b1111001001100000110100111110010 >
b10110 =
b1111001001100000110100111110010 /
b10110 .
b1000111111011001101101110001111 ;
1%
#510000
0%
#515000
b1111001001100000110100111110010 "
b1111001001100000110100111110010 4
b10110 &
b10110 0
b10110 7
0-
1%
#520000
0%
#525000
b1100111011101101001011011001110 ,
b1100111011101101001011011001110 3
b10111 +
b10111 2
1-
b1100111011101101001011011001110 >
b10111 =
b1100111011101101001011011001110 /
b10111 .
b1111001001100000110100111110010 ;
1%
#530000
0%
#535000
b1100111011101101001011011001110 "
b1100111011101101001011011001110 4
b10111 &
b10111 0
b10111 7
0-
1%
#540000
0%
#545000
b1110100000000000111101011101000 ,
b1110100000000000111101011101000 3
b11000 +
b11000 2
1-
b1110100000000000111101011101000 >
b11000 =
b1110100000000000111101011101000 /
b11000 .
b1100111011101101001011011001110 ;
1%
#550000
0%
#555000
b1110100000000000111101011101000 "
b1110100000000000111101011101000 4
b11000 &
b11000 0
b11000 7
0-
1%
#560000
0%
#565000
b1100010110010100100111011000101 ,
b1100010110010100100111011000101 3
b11001 +
b11001 2
1-
b1100010110010100100111011000101 >
b11001 =
b1100010110010100100111011000101 /
b11001 .
b1110100000000000111101011101000 ;
1%
#570000
0%
#575000
b1100010110010100100111011000101 "
b1100010110010100100111011000101 4
b11001 &
b11001 0
b11001 7
0-
1%
#580000
0%
#585000
b101110010110000100100101011100 ,
b101110010110000100100101011100 3
b11010 +
b11010 2
1-
b101110010110000100100101011100 >
b11010 =
b101110010110000100100101011100 /
b11010 .
b1100010110010100100111011000101 ;
1%
#590000
0%
#595000
b101110010110000100100101011100 "
b101110010110000100100101011100 4
b11010 &
b11010 0
b11010 7
0-
1%
#600000
0%
#605000
b1011110100011100010100010111101 ,
b1011110100011100010100010111101 3
b11011 +
b11011 2
1-
b1011110100011100010100010111101 >
b11011 =
b1011110100011100010100010111101 /
b11011 .
b101110010110000100100101011100 ;
1%
#610000
0%
#615000
b1011110100011100010100010111101 "
b1011110100011100010100010111101 4
b11011 &
b11011 0
b11011 7
0-
1%
#620000
0%
#625000
b10110101010110101100000101101 ,
b10110101010110101100000101101 3
b11100 +
b11100 2
1-
b10110101010110101100000101101 >
b11100 =
b10110101010110101100000101101 /
b11100 .
b1011110100011100010100010111101 ;
1%
#630000
0%
#635000
b10110101010110101100000101101 "
b10110101010110101100000101101 4
b11100 &
b11100 0
b11100 7
0-
1%
#640000
0%
#645000
b110010101001110010011001100101 ,
b110010101001110010011001100101 3
b11101 +
b11101 2
1-
b110010101001110010011001100101 >
b11101 =
b110010101001110010011001100101 /
b11101 .
b10110101010110101100000101101 ;
1%
#650000
0%
#655000
b110010101001110010011001100101 "
b110010101001110010011001100101 4
b11101 &
b11101 0
b11101 7
0-
1%
#660000
0%
#665000
b110001111011110110001001100011 ,
b110001111011110110001001100011 3
b11110 +
b11110 2
1-
b110001111011110110001001100011 >
b11110 =
b110001111011110110001001100011 /
b11110 .
b110010101001110010011001100101 ;
1%
#670000
0%
#675000
b110001111011110110001001100011 "
b110001111011110110001001100011 4
b11110 &
b11110 0
b11110 7
0-
1%
#680000
0%
#685000
b101011100111000011100001010 ,
b101011100111000011100001010 3
b11111 +
b11111 2
1-
b101011100111000011100001010 >
b11111 =
b101011100111000011100001010 /
b11111 .
b110001111011110110001001100011 ;
1%
#690000
0%
#695000
b101011100111000011100001010 "
b101011100111000011100001010 4
b11111 &
b11111 0
b11111 7
0-
1%
#700000
0%
#705000
b1000000001110110010001010000000 ,
b1000000001110110010001010000000 3
b0 +
b0 2
1-
b1000000001110110010001010000000 >
b0 =
b1000000001110110010001010000000 /
b0 .
b101011100111000011100001010 ;
1%
#710000
0%
#715000
b1000000001110110010001010000000 !
b1000000001110110010001010000000 5
b0 "
b0 4
b0 &
b0 0
1)
0(
b0 7
1:
09
0-
1%
#720000
0%
#725000
b10000011001000010000100100000 ,
b10000011001000010000100100000 3
b1 +
b1 2
1-
b10000011001000010000100100000 >
b1 =
b10000011001000010000100100000 /
b1 .
b1000000001110110010001010000000 <
b0 ;
1%
#730000
0%
#735000
b10000011001000010000100100000 !
b10000011001000010000100100000 5
b1 '
b1 1
b1 8
0-
1%
#740000
0%
#745000
b1010101011110000100010110101010 ,
b1010101011110000100010110101010 3
b10 +
b10 2
1-
b1010101011110000100010110101010 >
b10 =
b1010101011110000100010110101010 /
b10 .
b10000011001000010000100100000 <
1%
#750000
0%
#755000
b1010101011110000100010110101010 !
b1010101011110000100010110101010 5
b10 '
b10 1
b10 8
0-
1%
#760000
0%
#765000
b1001110110011001100110010011101 ,
b1001110110011001100110010011101 3
b11 +
b11 2
1-
b1001110110011001100110010011101 >
b11 =
b1001110110011001100110010011101 /
b11 .
b1010101011110000100010110101010 <
1%
#770000
0%
#775000
b1001110110011001100110010011101 !
b1001110110011001100110010011101 5
b11 '
b11 1
b11 8
0-
1%
#780000
0%
#785000
b1001011001000000011111010010110 ,
b1001011001000000011111010010110 3
b100 +
b100 2
1-
b1001011001000000011111010010110 >
b100 =
b1001011001000000011111010010110 /
b100 .
b1001110110011001100110010011101 <
1%
#790000
0%
#795000
b1001011001000000011111010010110 !
b1001011001000000011111010010110 5
b100 '
b100 1
b100 8
0-
1%
#800000
0%
#805000
b1001100000111011100000010011 ,
b1001100000111011100000010011 3
b101 +
b101 2
1-
b1001100000111011100000010011 >
b101 =
b1001100000111011100000010011 /
b101 .
b1001011001000000011111010010110 <
1%
#810000
0%
#815000
b1001100000111011100000010011 !
b1001100000111011100000010011 5
b101 '
b101 1
b101 8
0-
1%
#820000
0%
#825000
b110101111000011100000001101 ,
b110101111000011100000001101 3
b110 +
b110 2
1-
b110101111000011100000001101 >
b110 =
b110101111000011100000001101 /
b110 .
b1001100000111011100000010011 <
1%
#830000
0%
#835000
b110101111000011100000001101 !
b110101111000011100000001101 5
b110 '
b110 1
b110 8
0-
1%
#840000
0%
#845000
b101001101001111101011001010011 ,
b101001101001111101011001010011 3
b111 +
b111 2
1-
b101001101001111101011001010011 >
b111 =
b101001101001111101011001010011 /
b111 .
b110101111000011100000001101 <
1%
#850000
0%
#855000
b101001101001111101011001010011 !
b101001101001111101011001010011 5
b111 '
b111 1
b111 8
0-
1%
#860000
0%
#865000
b110101100111111101110101101011 ,
b110101100111111101110101101011 3
b1000 +
b1000 2
1-
b110101100111111101110101101011 >
b1000 =
b110101100111111101110101101011 /
b1000 .
b101001101001111101011001010011 <
1%
#870000
0%
#875000
b110101100111111101110101101011 !
b110101100111111101110101101011 5
b1000 '
b1000 1
b1000 8
0-
1%
#880000
0%
#885000
b1101010101001100010101011010101 ,
b1101010101001100010101011010101 3
b1001 +
b1001 2
1-
b1101010101001100010101011010101 >
b1001 =
b1101010101001100010101011010101 /
b1001 .
b110101100111111101110101101011 <
1%
#890000
0%
#895000
b1101010101001100010101011010101 !
b1101010101001100010101011010101 5
b1001 '
b1001 1
b1001 8
0-
1%
#900000
0%
#905000
b1000101110100101000000010 ,
b1000101110100101000000010 3
b1010 +
b1010 2
1-
b1000101110100101000000010 >
b1010 =
b1000101110100101000000010 /
b1010 .
b1101010101001100010101011010101 <
1%
#910000
0%
#915000
b1000101110100101000000010 !
b1000101110100101000000010 5
b1010 '
b1010 1
b1010 8
0-
1%
#920000
0%
#925000
b1010111010101100011111010101110 ,
b1010111010101100011111010101110 3
b1011 +
b1011 2
1-
b1010111010101100011111010101110 >
b1011 =
b1010111010101100011111010101110 /
b1011 .
b1000101110100101000000010 <
1%
#930000
0%
#935000
b1010111010101100011111010101110 !
b1010111010101100011111010101110 5
b1011 '
b1011 1
b1011 8
0-
1%
#940000
0%
#945000
b1110111111111110100100011101 ,
b1110111111111110100100011101 3
b1100 +
b1100 2
1-
b1110111111111110100100011101 >
b1100 =
b1110111111111110100100011101 /
b1100 .
b1010111010101100011111010101110 <
1%
#950000
0%
#955000
b1110111111111110100100011101 !
b1110111111111110100100011101 5
b1100 '
b1100 1
b1100 8
0-
1%
#960000
0%
#965000
b1100111110001010111001011001111 ,
b1100111110001010111001011001111 3
b1101 +
b1101 2
1-
b1100111110001010111001011001111 >
b1101 =
b1100111110001010111001011001111 /
b1101 .
b1110111111111110100100011101 <
1%
#970000
0%
#975000
b1100111110001010111001011001111 !
b1100111110001010111001011001111 5
b1101 '
b1101 1
b1101 8
0-
1%
#980000
0%
#985000
b10001100001000100100100100011 ,
b10001100001000100100100100011 3
b1110 +
b1110 2
1-
b10001100001000100100100100011 >
b1110 =
b10001100001000100100100100011 /
b1110 .
b1100111110001010111001011001111 <
1%
#990000
0%
#995000
b10001100001000100100100100011 !
b10001100001000100100100100011 5
b1110 '
b1110 1
b1110 8
0-
1%
#1000000
0%
#1005000
b101000010010110010100001010 ,
b101000010010110010100001010 3
b1111 +
b1111 2
1-
b101000010010110010100001010 >
b1111 =
b101000010010110010100001010 /
b1111 .
b10001100001000100100100100011 <
1%
#1010000
0%
#1015000
b101000010010110010100001010 !
b101000010010110010100001010 5
b1111 '
b1111 1
b1111 8
0-
1%
#1020000
0%
#1025000
b1100101011100110000101011001010 ,
b1100101011100110000101011001010 3
b10000 +
b10000 2
1-
b1100101011100110000101011001010 >
b10000 =
b1100101011100110000101011001010 /
b10000 .
b101000010010110010100001010 <
1%
#1030000
0%
#1035000
b1100101011100110000101011001010 !
b1100101011100110000101011001010 5
b10000 '
b10000 1
b10000 8
0-
1%
#1040000
0%
#1045000
b11110001100010100110000111100 ,
b11110001100010100110000111100 3
b10001 +
b10001 2
1-
b11110001100010100110000111100 >
b10001 =
b11110001100010100110000111100 /
b10001 .
b1100101011100110000101011001010 <
1%
#1050000
0%
#1055000
b11110001100010100110000111100 !
b11110001100010100110000111100 5
b10001 '
b10001 1
b10001 8
0-
1%
#1060000
0%
#1065000
b1111001011010001011110111110010 ,
b1111001011010001011110111110010 3
b10010 +
b10010 2
1-
b1111001011010001011110111110010 >
b10010 =
b1111001011010001011110111110010 /
b10010 .
b11110001100010100110000111100 <
1%
#1070000
0%
#1075000
b1111001011010001011110111110010 !
b1111001011010001011110111110010 5
b10010 '
b10010 1
b10010 8
0-
1%
#1080000
0%
#1085000
b1000101001011100110000110001010 ,
b1000101001011100110000110001010 3
b10011 +
b10011 2
1-
b1000101001011100110000110001010 >
b10011 =
b1000101001011100110000110001010 /
b10011 .
b1111001011010001011110111110010 <
1%
#1090000
0%
#1095000
b1000101001011100110000110001010 !
b1000101001011100110000110001010 5
b10011 '
b10011 1
b10011 8
0-
1%
#1100000
0%
#1105000
b100000110001001011001101000001 ,
b100000110001001011001101000001 3
b10100 +
b10100 2
1-
b100000110001001011001101000001 >
b10100 =
b100000110001001011001101000001 /
b10100 .
b1000101001011100110000110001010 <
1%
#1110000
0%
#1115000
b100000110001001011001101000001 !
b100000110001001011001101000001 5
b10100 '
b10100 1
b10100 8
0-
1%
#1120000
0%
#1125000
b1101100010010110011010011011000 ,
b1101100010010110011010011011000 3
b10101 +
b10101 2
1-
b1101100010010110011010011011000 >
b10101 =
b1101100010010110011010011011000 /
b10101 .
b100000110001001011001101000001 <
1%
#1130000
0%
#1135000
b1101100010010110011010011011000 !
b1101100010010110011010011011000 5
b10101 '
b10101 1
b10101 8
0-
1%
#1140000
0%
#1145000
b111100001000001111001101111000 ,
b111100001000001111001101111000 3
b10110 +
b10110 2
1-
b111100001000001111001101111000 >
b10110 =
b111100001000001111001101111000 /
b10110 .
b1101100010010110011010011011000 <
1%
#1150000
0%
#1155000
b111100001000001111001101111000 !
b111100001000001111001101111000 5
b10110 '
b10110 1
b10110 8
0-
1%
#1160000
0%
#1165000
b1000100100010100001001010001001 ,
b1000100100010100001001010001001 3
b10111 +
b10111 2
1-
b1000100100010100001001010001001 >
b10111 =
b1000100100010100001001010001001 /
b10111 .
b111100001000001111001101111000 <
1%
#1170000
0%
#1175000
b1000100100010100001001010001001 !
b1000100100010100001001010001001 5
b10111 '
b10111 1
b10111 8
0-
1%
#1180000
0%
#1185000
b1110101110001010000110111101011 ,
b1110101110001010000110111101011 3
b11000 +
b11000 2
1-
b1110101110001010000110111101011 >
b11000 =
b1110101110001010000110111101011 /
b11000 .
b1000100100010100001001010001001 <
1%
#1190000
0%
#1195000
b1110101110001010000110111101011 !
b1110101110001010000110111101011 5
b11000 '
b11000 1
b11000 8
0-
1%
#1200000
0%
#1205000
b1011011000000100110010110110110 ,
b1011011000000100110010110110110 3
b11001 +
b11001 2
1-
b1011011000000100110010110110110 >
b11001 =
b1011011000000100110010110110110 /
b11001 .
b1110101110001010000110111101011 <
1%
#1210000
0%
#1215000
b1011011000000100110010110110110 !
b1011011000000100110010110110110 5
b11001 '
b11001 1
b11001 8
0-
1%
#1220000
0%
#1225000
b1100011010010111111100111000110 ,
b1100011010010111111100111000110 3
b11010 +
b11010 2
1-
b1100011010010111111100111000110 >
b11010 =
b1100011010010111111100111000110 /
b11010 .
b1011011000000100110010110110110 <
1%
#1230000
0%
#1235000
b1100011010010111111100111000110 !
b1100011010010111111100111000110 5
b11010 '
b11010 1
b11010 8
0-
1%
#1240000
0%
#1245000
b1010111000101010001001110101110 ,
b1010111000101010001001110101110 3
b11011 +
b11011 2
1-
b1010111000101010001001110101110 >
b11011 =
b1010111000101010001001110101110 /
b11011 .
b1100011010010111111100111000110 <
1%
#1250000
0%
#1255000
b1010111000101010001001110101110 !
b1010111000101010001001110101110 5
b11011 '
b11011 1
b11011 8
0-
1%
#1260000
0%
#1265000
b1011110011101010000001010111100 ,
b1011110011101010000001010111100 3
b11100 +
b11100 2
1-
b1011110011101010000001010111100 >
b11100 =
b1011110011101010000001010111100 /
b11100 .
b1010111000101010001001110101110 <
1%
#1270000
0%
#1275000
b1011110011101010000001010111100 !
b1011110011101010000001010111100 5
b11100 '
b11100 1
b11100 8
0-
1%
#1280000
0%
#1285000
b10101000011111101110100101010 ,
b10101000011111101110100101010 3
b11101 +
b11101 2
1-
b10101000011111101110100101010 >
b11101 =
b10101000011111101110100101010 /
b11101 .
b1011110011101010000001010111100 <
1%
#1290000
0%
#1295000
b10101000011111101110100101010 !
b10101000011111101110100101010 5
b11101 '
b11101 1
b11101 8
0-
1%
#1300000
0%
#1305000
b101110101111001101000001011 ,
b101110101111001101000001011 3
b11110 +
b11110 2
1-
b101110101111001101000001011 >
b11110 =
b101110101111001101000001011 /
b11110 .
b10101000011111101110100101010 <
1%
#1310000
0%
#1315000
b101110101111001101000001011 !
b101110101111001101000001011 5
b11110 '
b11110 1
b11110 8
0-
1%
#1320000
0%
#1325000
b111000100101111011111001110001 ,
b111000100101111011111001110001 3
b11111 +
b11111 2
1-
b111000100101111011111001110001 >
b11111 =
b111000100101111011111001110001 /
b11111 .
b101110101111001101000001011 <
1%
#1330000
0%
#1335000
b111000100101111011111001110001 !
b111000100101111011111001110001 5
b11111 '
b11111 1
b11111 8
0-
1%
#1340000
0%
#1345000
b100000 .
b111000100101111011111001110001 <
1%
